cfw_fido-1.6.0rc3.dist-info/DESCRIPTION.rst
cfw_fido-1.6.0rc3.dist-info/METADATA
cfw_fido-1.6.0rc3.dist-info/RECORD
cfw_fido-1.6.0rc3.dist-info/WHEEL
cfw_fido-1.6.0rc3.dist-info/entry_points.txt
cfw_fido-1.6.0rc3.dist-info/metadata.json
cfw_fido-1.6.0rc3.dist-info/top_level.txt
fido/__init__.py
fido/char_handler.py
fido/fido.py
fido/package.py
fido/prepare.py
fido/toxml.py
fido/update_signatures.py
fido/versions.py
fido/conf/DROID_SignatureFile-v104.xml
fido/conf/container-signature-20200121.xml
fido/conf/dc.xsd
fido/conf/dcmitype.xsd
fido/conf/dcterms.xsd
fido/conf/fido-formats.xsd
fido/conf/format_extension_template.xml
fido/conf/format_extensions.xml
fido/conf/formats-v104.xml
fido/conf/pronom-xml-v104.zip
fido/conf/versions.xml
fido/pronom/__init__.py
fido/pronom/http.py
fido/pronom/soap.py
