Metadata-Version: 2.0
Name: cfw-fido
Version: 1.6.0rc3
Summary: Format Identification for Digital Objects (FIDO).
Home-page: http://openpreservation.org/technology/products/fido/
Author: Adam Farquhar (BL), 2010
License: Apache License 2.0
Platform: UNKNOWN
Classifier: Development Status :: 5 - Production/Stable
Classifier: Environment :: Console
Classifier: License :: OSI Approved :: Apache Software License
Classifier: Programming Language :: Python :: 2
Classifier: Programming Language :: Python :: 2.7
Provides-Extra: testing
Provides-Extra: setup
License-File: LICENSE.txt
Requires-Dist: importlib-resources
Requires-Dist: olefile (>=0.46,<1)
Requires-Dist: requests
Requires-Dist: six (<2,>=1.10.0)
Requires-Dist: win-unicode-console (>=0.5); python_version == "2.7" and platform_system == "Windows"
Provides-Extra: setup
Requires-Dist: pytest-runner; extra == 'setup'
Provides-Extra: testing
Requires-Dist: flake8; extra == 'testing'
Requires-Dist: pep257; extra == 'testing'
Requires-Dist: pylint; extra == 'testing'
Requires-Dist: pytest; extra == 'testing'
Requires-Dist: pytest-cov; extra == 'testing'
